client/__init__.py
client/client_main.py
client/client/__init__.py
client/client/add_contact.py
client/client/database.py
client/client/del_contact.py
client/client/main_window.py
client/client/main_window_conv.py
client/client/start_dialog.py
client/client/transport.py
client/common/__init__.py
client/common/constants.py
client/common/decorators.py
client/common/descriptors.py
client/common/errors.py
client/common/metaclasses.py
client/common/utils.py
client/log/__init__.py
client/log/client_log_config.py
client/log/server_log_config.py
client/unit_tests/__init__.py
client/unit_tests/test_client.py
client/unit_tests/test_server.py
client/unit_tests/test_utils.py
py_simple_messenger_client-0.0.1.dist-info/METADATA
py_simple_messenger_client-0.0.1.dist-info/WHEEL
py_simple_messenger_client-0.0.1.dist-info/top_level.txt
py_simple_messenger_client-0.0.1.dist-info/RECORD
